setup.py
src/django_staticfiles_jquery_ui.egg-info/PKG-INFO
src/django_staticfiles_jquery_ui.egg-info/SOURCES.txt
src/django_staticfiles_jquery_ui.egg-info/dependency_links.txt
src/django_staticfiles_jquery_ui.egg-info/not-zip-safe
src/django_staticfiles_jquery_ui.egg-info/requires.txt
src/django_staticfiles_jquery_ui.egg-info/top_level.txt
src/jquery_ui/__init__.py
src/jquery_ui/static/jquery_ui/AUTHORS.txt
src/jquery_ui/static/jquery_ui/GPL-LICENSE.txt
src/jquery_ui/static/jquery_ui/MANIFEST
src/jquery_ui/static/jquery_ui/MIT-LICENSE.txt
src/jquery_ui/static/jquery_ui/jquery-ui.js
src/jquery_ui/static/jquery_ui/jquery-ui.min.js
src/jquery_ui/static/jquery_ui/package.json
src/jquery_ui/static/jquery_ui/i18n/jquery-ui-i18n.js
src/jquery_ui/static/jquery_ui/i18n/jquery-ui-i18n.min.js
src/jquery_ui/static/jquery_ui/i18n/jquery.ui.datepicker-af.js
src/jquery_ui/static/jquery_ui/i18n/jquery.ui.datepicker-af.min.js
src/jquery_ui/static/jquery_ui/i18n/jquery.ui.datepicker-ar-DZ.js
src/jquery_ui/static/jquery_ui/i18n/jquery.ui.datepicker-ar-DZ.min.js
src/jquery_ui/static/jquery_ui/i18n/jquery.ui.datepicker-ar.js
src/jquery_ui/static/jquery_ui/i18n/jquery.ui.datepicker-ar.min.js
src/jquery_ui/static/jquery_ui/i18n/jquery.ui.datepicker-az.js
src/jquery_ui/static/jquery_ui/i18n/jquery.ui.datepicker-az.min.js
src/jquery_ui/static/jquery_ui/i18n/jquery.ui.datepicker-bg.js
src/jquery_ui/static/jquery_ui/i18n/jquery.ui.datepicker-bg.min.js
src/jquery_ui/static/jquery_ui/i18n/jquery.ui.datepicker-bs.js
src/jquery_ui/static/jquery_ui/i18n/jquery.ui.datepicker-bs.min.js
src/jquery_ui/static/jquery_ui/i18n/jquery.ui.datepicker-ca.js
src/jquery_ui/static/jquery_ui/i18n/jquery.ui.datepicker-ca.min.js
src/jquery_ui/static/jquery_ui/i18n/jquery.ui.datepicker-cs.js
src/jquery_ui/static/jquery_ui/i18n/jquery.ui.datepicker-cs.min.js
src/jquery_ui/static/jquery_ui/i18n/jquery.ui.datepicker-cy-GB.js
src/jquery_ui/static/jquery_ui/i18n/jquery.ui.datepicker-cy-GB.min.js
src/jquery_ui/static/jquery_ui/i18n/jquery.ui.datepicker-da.js
src/jquery_ui/static/jquery_ui/i18n/jquery.ui.datepicker-da.min.js
src/jquery_ui/static/jquery_ui/i18n/jquery.ui.datepicker-de.js
src/jquery_ui/static/jquery_ui/i18n/jquery.ui.datepicker-de.min.js
src/jquery_ui/static/jquery_ui/i18n/jquery.ui.datepicker-el.js
