Metadata-Version: 1.1
Name: django-staticfiles-jquery-ui
Version: 1.8.24
Summary: jquery-ui packaged for django-staticfiles
Home-page: http://byteorbit.com/
Author: Byte Orbit
Author-email: admin@byteorbit.com
License: BSD
Platform: UNKNOWN
Classifier: Development Status :: 5 - Production/Stable
Classifier: Environment :: Web Environment
Classifier: Programming Language :: Python
Classifier: Framework :: Django
